fastone_ucloud/__init__.py
fastone_ucloud/cli.py
fastone_ucloud/fastone_ucloud.py
fastone_ucloud/utils.py
fastone_ucloud-0.1.2.dist-info/AUTHORS.rst
fastone_ucloud-0.1.2.dist-info/LICENSE
fastone_ucloud-0.1.2.dist-info/METADATA
fastone_ucloud-0.1.2.dist-info/WHEEL
fastone_ucloud-0.1.2.dist-info/entry_points.txt
fastone_ucloud-0.1.2.dist-info/top_level.txt
fastone_ucloud-0.1.2.dist-info/RECORD
