Metadata-Version: 2.1
Name: fastone-ucloud
Version: 0.1.2
Summary: ucloud deployment services that work on FastOne stack for computing service
Home-page: https://github.com/neocxf/fastone_ucloud
Author: Xiaofei Chen
Author-email: neocxf@qq.com
License: MIT license
Keywords: fastone_ucloud
Platform: UNKNOWN
Classifier: Development Status :: 2 - Pre-Alpha
Classifier: Intended Audience :: Developers
Classifier: License :: OSI Approved :: MIT License
Classifier: Natural Language :: English
Classifier: Programming Language :: Python :: 2
Classifier: Programming Language :: Python :: 3
Classifier: Programming Language :: Python :: 3.5
Classifier: Programming Language :: Python :: 3.6
Classifier: Programming Language :: Python :: 3.7
Classifier: Programming Language :: Python :: 3.8
Requires-Python: >=2
Requires-Dist: Click (>=7.0)
Requires-Dist: six (>=1.15.0)
